{
    "profileName": "RAJATH R PATIL",
    "jobTitle": "Frontend Developer",
    "skillsImages": [
        "/images/icons/icons8-html-5-48.png",
        "/images/icons/icons8-css-48.png",
        "/images/icons/icons8-javascript-48.png",
        "/images/icons/icons8-angular-48.png",
        "/images/icons/icons8-react-80.png",
        "/images/icons/icons8-visual-studio-code-2019-48.png"
    ],
    "profileImage": "/images/profile-image.jpg",
    "summery": "Accomplished Front-End Developer with 3+ years of experience in building scalable Single Page Applications. Expertise in the modern front-end stack, including Angular, React with Next.js. Proven ability to improve performance, enhance SEO, and streamline development processes through best practices for optimizing scalable web applications.",
    "skills": [
        {
            "skillDomain": "Frontend",
            "skillKeys": [
                {
                    "key": "HTML",
                    "image": "/images/icons/icons8-html-5-48.png",
                    "route": "#"
                },
                {
                    "key": "CSS",
                    "image": "/images/icons/icons8-css-48.png",
                    "route": "#"
                },
                {
                    "key": "JAVASCRIPT",
                    "image": "/images/icons/icons8-javascript-48.png",
                    "route": "#"
                },
                {
                    "key": "ANGULAR",
                    "image": "/images/icons/icons8-angular-48.png",
                    "route": "#"
                },
                {
                    "key": "REACT & NEXTJS",
                    "image": "/images/icons/icons8-react-80.png",
                    "route": "#"
                },
                {
                    "key": "TYPESCRIPT",
                    "image": "/images/icons/icons8-typescript-48.png",
                    "route": "#"
                }
            ]
        },
        {
            "skillDomain": "Backend",
            "skillKeys": [
                {
                    "key": "Node.js",
                    "image": "/images/icons/icon-nodejs.jpeg",
                    "route": "#"
                }
            ]
        },
        {
            "skillDomain": "UI",
            "skillKeys": [
                {
                    "key": "BOOTSTRAP",
                    "image": "/images/icons/icons8-bootstrap-48.png",
                    "route": "#"
                },
                {
                    "key": "TAILWIND",
                    "image": "/images/icons/icons8-tailwind-css-48.png",
                    "route": "#"
                },
                {
                    "key": "MATERIAL UI",
                    "image": "/images/icons/icons8-material-ui-48.png",
                    "route": "#"
                }
            ]
        },
        {
            "skillDomain": "Tools",
            "skillKeys": [
                {
                    "key": "VISUAL STUDIOS",
                    "image": "/images/icons/icons8-visual-studio-code-2019-48.png",
                    "route": "#"
                },
                {
                    "key": "POST MAN",
                    "image": "/images/icons/icons8-postman-api-64.png",
                    "route": "#"
                },
                {
                    "key": "JIRA",
                    "image": "/images/icons/icons8-jira-48.png",
                    "route": "#"
                },
                {
                    "key": "BITBUCKET",
                    "image": "/images/icons/icons8-bitbucket-is-a-web-based-version-control-repository-hosting-service-48.png",
                    "route": "#"
                },
                {
                    "key": "GIT",
                    "image": "/images/icons/icons8-git-48.png",
                    "route": "#"
                }
            ]
        },
        {
            "skillDomain": "Package Manager",
            "skillKeys": [
                {
                    "key": "NPM",
                    "image": "/images/icons/icons8-npm-48.png",
                    "route": "#"
                }
            ]
        }
    ],
    "contact": [
        {
            "key": "Gmail",
            "image": "/images/icons/icons8-gmail-48.png",
            "route": "https://mail.google.com/mail/?view=cm&fs=1&to=yathrika2pi@gmail.com"
        },
        {
            "key": "LinkedIn",
            "image": "/images/icons/icons8-linkedin-48.png",
            "route": "https://www.linkedin.com/in/rajath-r-patil-web-developer/"
        }
    ],
    "workExperienceData": [
        {
            "companyName": "Hash Connect Integrated Services",
            "place": "Bangalore, India",
            "workType": "Full-time",
            "totalWorkingYears": "Jan-2026 to Present",
            "companyLogo": "images/appcontent/experience3.png",
            "designations": [
                {
                    "designationName": "Software Developer",
                    "servedTime": "Jan-2024 to Present"
                }
            ],
            "rolesAndResponsibilities": [
                "Working in immence integrations over Lead management system, Product Information Management, Online Reputation Management Store locators and much more..."
            ]
        },
        {
            "companyName": "HealthSignz Technologies Pvt Ltd",
            "place": "Bangalore, India",
            "workType": "Full-time",
            "totalWorkingYears": "Nov-2022 to Dec 2026",
            "companyLogo": "/images/icons/company1_logo.jpg",
            "designations": [
                {
                    "designationName": "Software Engineer",
                    "servedTime": "May-2024 to Present"
                }
            ],
            "rolesAndResponsibilities": [
                "Spearheaded the entire SDLC for high-performance web applications, managing feature delivery from requirement analysis to production deployment via Jenkins for Continuous Integration and Continuous Deployment (CI/CD).",
                "Utilized deep knowledge of React and Angular best practices and modern architecture patterns to build scalable and maintainable features within the product suite.",
                "Collaborated across Engineering and Product teams to translate high-level requirements into scalable Front-End solutions, ensuring a unified user experience(UX/UI) across the product suite.",
                "Integrated dozens of RESTful APIs and third-party libraries, leveraging TypeScript and TDD best practices to guarantee code quality and stability for new features.",
                "Executed and monitored build deployments, contributing to a 99.9% uptime for critical application updates and new features, ensuring a smooth and reliable delivery process under Agile Methodology.",
                "Optimized page load speeds by 20% across the main application through code splitting and memoization, directly enhancing core application efficiency and user retention.",
                "Communicated complex technical requirements to non-technical business partners to establish strategic partnerships, resulting in new feature implementations that contributed to revenue increase."
            ]
        },
        
        {
            "companyName": "HealthSignz Technologies Pvt Ltd",
            "place": "Bangalore, India",
            "workType": "Full-time",
            "totalWorkingYears": "Nov-2022 to Dec 2026",
            "companyLogo": "/images/icons/company1_logo.jpg",
            "designations": [
                {
                    "designationName": "Trainee Software Engineer",
                    "servedTime": "Nov-2022 to Aril-2024"
                }
            ],
            "rolesAndResponsibilities": [
                "Implemented user-friendly web applications focusing on user interface design using HTML, CSS, TypeScript(a superset of JavaScript), with Angular and React.js libraries.",
                "Collaborated with cross-functional teams, including backend developers and UX designers, to build successful products.",
                "Interacting with clients, gathered their valuable business input, and converted their ideas into functional user interfaces."
            ]
        }
    ],
    "projects": [
        {
            "title": "Consumer-Apps",
            "subTitle": "B2C Web Application: React.js (18+), Next.js (14+), Redux, Zustand, Tailwind CSS",
            "description": [
                "Architected and developed a high-performance web application, improving page load speed by 40% through a hybrid rendering strategy (SSG, SSR, CSR), lazy loading, and memoization (validated by Google Lighthouse).",
                "Implemented complex state logic using Redux Toolkit and Zustand for specific module requirements, ensuring predictable and centralized data flow.",
                "Enhanced SEO and search engine crawlability by implementing schema markup and collaborated with industry leaders to deliver custom solutions."
            ]
        },
        {
            "title": "MyMedic/Super-app",
            "subTitle": "Enterprise SaaS B2B Platform: Angular (8, 16+), TypeScript, Bootstrap",
            "description": [
                "Built a scalable B2B SaaS platform that streamlined slot booking and order management for diagnostic, pharmacy, and doctor modules, enhancing operational efficiency and reducing product creation time for new subscribers.",
                "Architected the platform using a micro-frontend approach (if applicable in Angular, mention this) and leveraged the Angular CLI for efficient project management and build optimization.",
                "Led customization for high-profile clients and integrated Firebase Cloud Messaging to enable real-time notifications, significantly improving user engagement."
            ]
        },
         {
            "title": "Personal Projects",
            "subTitle": "Enterprise SaaS B2B Platform: Angular (8, 16+), TypeScript, Bootstrap",
            "description": [
                "Portfolio : https://my-domain-silk.vercel.app/",
                "Business Dashboard: https://my-ecommerce-dashboard-4od4.vercel.app/",
                "Other mini-Projects: https://web-app-fetures.vercel.app/"
            ]
        }
    ],
    "education": [
        {
            "specialization": "Industrial And Production Engineer",
            "Collage": "University BDT College Of Engineering",
            "place": "Davangere, Karnataka, India",
            "graduateYear": "2020"
        }
    ]
}
